com/softalks/sh.py
com.softalks.sh-1.0.0.dist-info/METADATA
com.softalks.sh-1.0.0.dist-info/WHEEL
com.softalks.sh-1.0.0.dist-info/top_level.txt
com.softalks.sh-1.0.0.dist-info/RECORD
