Metadata-Version: 2.1
Name: com.softalks.sh
Version: 1.0.0
Summary: CLI Shell utilities for Python 3
Author-email: Santiago Ruiz <hiebra@hotmail.com>
Requires-Dist: com.softalks.debug (<2,>=1)
